blackjack/__init__.py
blackjack/__main__.py
blackjack/cli.py
blackjack/game.py
blackjack/game_objects.py
blackjack/utils.py
x10_blackjack-1.1.4.dist-info/LICENSE
x10_blackjack-1.1.4.dist-info/METADATA
x10_blackjack-1.1.4.dist-info/WHEEL
x10_blackjack-1.1.4.dist-info/entry_points.txt
x10_blackjack-1.1.4.dist-info/top_level.txt
x10_blackjack-1.1.4.dist-info/RECORD
