Metadata-Version: 2.1
Name: x10-blackjack
Version: 1.1.4
Summary: A small blackjack game.
Home-page: https://gitlab.com/x10an14/blackjack
Author-email: x10an14@gmail.com
License: UNKNOWN
Platform: UNKNOWN
Classifier: License :: OSI Approved :: Apache Software License
Classifier: Programming Language :: Python :: 3
Classifier: Programming Language :: Python :: 3.7
Classifier: Operating System :: OS Independent
Classifier: Topic :: Games/Entertainment
Classifier: Topic :: Software Development
Requires-Python: >=3.7
Requires-Dist: click (<8,>=7)
Requires-Dist: requests (<3,>=2)
Requires-Dist: tabulate (==0.8.7)
